heyvi/__init__.py
heyvi/detection.py
heyvi/label.py
heyvi/recognition.py
heyvi/sensor.py
heyvi/system.py
heyvi/util.py
heyvi/version.py
heyvi/model/__init__.py
heyvi/model/ResNets_3D_PyTorch/__init__.py
heyvi/model/ResNets_3D_PyTorch/resnet.py
heyvi/model/cap/background_class_to_index.csv
heyvi/model/cap/background_index_to_class.csv
heyvi/model/cap/background_index_to_training_weight.csv
heyvi/model/cap/cap_classification_pad_class.csv
heyvi/model/cap/cap_classification_pad_coarsened_class.csv
heyvi/model/cap/cap_classification_pad_stabilize_class.csv
heyvi/model/cap/cap_classification_pad_stabilize_training_weight.csv
heyvi/model/cap/cap_classification_pad_training_weight.csv
heyvi/model/cap/class.csv
heyvi/model/cap/class_to_shortlabel.csv
heyvi/model/cap/class_to_training_weight.csv
heyvi/model/cap/coarse_class_to_index.csv
heyvi/model/cap/coarse_index_to_class.csv
heyvi/model/cap/coarse_index_to_training_weight.csv
heyvi/model/cap/index_to_meva_training_weight.csv
heyvi/model/cap/joint_background_index_to_training_weight.csv
heyvi/model/face/__init__.py
heyvi/model/face/detection.py
heyvi/model/face/faster_rcnn.py
heyvi/model/face/recognition.py
heyvi/model/yolov3/__init__.py
heyvi/model/yolov3/coco.names
heyvi/model/yolov3/network.py
heyvi/model/yolov3/utils/__init__.py
heyvi/model/yolov3/utils/parse_config.py
heyvi/model/yolov3/utils/utils.py
heyvi/model/yolov5/__init__.py
heyvi/model/yolov5/coco.names
heyvi/model/yolov5/models/__init__.py
heyvi/model/yolov5/models/common.py
heyvi/model/yolov5/models/experimental.py
heyvi/model/yolov5/models/export.py
heyvi/model/yolov5/models/yolo.py
heyvi/model/yolov5/models/yolov5l.yaml
heyvi/model/yolov5/models/yolov5m.yaml
heyvi/model/yolov5/models/yolov5s.yaml
heyvi/model/yolov5/models/yolov5x.yaml
heyvi/model/yolov5/utils/__init__.py
heyvi/model/yolov5/utils/activations.py
heyvi/model/yolov5/utils/autoanchor.py
heyvi/model/yolov5/utils/general.py
heyvi/model/yolov5/utils/google_utils.py
heyvi-0.2.28.dist-info/LICENSE
heyvi-0.2.28.dist-info/METADATA
heyvi-0.2.28.dist-info/WHEEL
heyvi-0.2.28.dist-info/top_level.txt
heyvi-0.2.28.dist-info/RECORD
