Metadata-Version: 2.1
Name: heyvi
Version: 0.2.28
Summary: Project Vi
Home-page: https://github.com/visym/heyvi
Download-URL: https://github.com/visym/heyvi/archive/0.2.28.tar.gz
Author: Visym Labs
Author-email: info@visym.com
Keywords: computer vision machine learning ML CV privacy video image
Classifier: Programming Language :: Python :: 3
Classifier: Operating System :: OS Independent
License-File: LICENSE
Requires-Dist: vipy
Requires-Dist: pycollector
Requires-Dist: torch
Requires-Dist: torchvision
Requires-Dist: pyyaml
Requires-Dist: pytorch-lightning
Requires-Dist: ujson
Provides-Extra: all
Requires-Dist: pdoc3 ; extra == 'all'
